mcp_server_greeter/__init__.py
mcp_server_greeter/main.py
mcp_server_greeter-0.1.5.dist-info/licenses/LICENSE
mcp_server_greeter-0.1.5.dist-info/METADATA
mcp_server_greeter-0.1.5.dist-info/WHEEL
mcp_server_greeter-0.1.5.dist-info/entry_points.txt
mcp_server_greeter-0.1.5.dist-info/top_level.txt
mcp_server_greeter-0.1.5.dist-info/RECORD
