Metadata-Version: 2.4
Name: mcp-server-greeter
Version: 0.1.5
Summary: A simple MCP server that greets you
Author-email: Adon Mathew <adon.pmpm@gmail.com>
License: MIT
Requires-Python: >=3.10
License-File: LICENSE
Requires-Dist: mcp>=1.12.4
Dynamic: license-file
